holtair/__init__.py
holtair/_exceptions.py
holtair/_image_reading.py
holtair/_sleep_detection.py
holtair/_statistics.py
holtair/_text_reading.py
holtair/exams.py
holtair-1.0.4.dist-info/METADATA
holtair-1.0.4.dist-info/WHEEL
holtair-1.0.4.dist-info/licenses/LICENSE
holtair-1.0.4.dist-info/RECORD
