Metadata-Version: 2.1
Name: holtair
Version: 1.0.4
Summary: Package for reading data from Holter blood pressure test results.
Project-URL: Homepage, https://github.com/bsinski/HoltAir-package
Author-email: Bartosz Siński <sinski.bartek00@gmail.com>
License-File: LICENSE
Classifier: License :: OSI Approved :: MIT License
Classifier: Operating System :: OS Independent
Classifier: Programming Language :: Python :: 3
Requires-Python: >=3.7
